featherplot/__init__.py
featherplot/_modidx.py
featherplot/commands.py
featherplot/constants.py
featherplot/dataclasses.py
featherplot/deepscatter.py
featherplot/files.py
featherplot/paths.py
featherplot/rich.py
featherplot/typer.py
featherplot/types.py
featherplot/utils.py
featherplot-0.0.6.dist-info/LICENSE
featherplot-0.0.6.dist-info/METADATA
featherplot-0.0.6.dist-info/WHEEL
featherplot-0.0.6.dist-info/entry_points.txt
featherplot-0.0.6.dist-info/top_level.txt
featherplot-0.0.6.dist-info/RECORD
