Metadata-Version: 2.1
Name: featherplot
Version: 0.0.6
Summary: featherplot
Home-page: https://github.com/dsm-72/featherplot-py
Author: dsm-72
Author-email: sumner.magruder@yale.edu
License: Apache Software License 2.0
Keywords: featherplot feather pyarrow arrow feather-format parquet parquet-format anndata single cell
Classifier: Development Status :: 4 - Beta
Classifier: Intended Audience :: Developers
Classifier: Natural Language :: English
Classifier: Programming Language :: Python :: 3.11
Classifier: License :: OSI Approved :: Apache Software License
Requires-Python: >=3.11
License-File: LICENSE
Requires-Dist: pyarrow
Requires-Dist: rich
Requires-Dist: typer
Requires-Dist: numpy (>1.22)
Requires-Dist: anndata
Provides-Extra: dev
